catway/__init__.py
catway/async_session.py
catway/asyncio.py
catway/session.py
catway/types.py
catway/utils.py
catway-1.1.dist-info/LICENSE
catway-1.1.dist-info/METADATA
catway-1.1.dist-info/WHEEL
catway-1.1.dist-info/top_level.txt
catway-1.1.dist-info/RECORD
