Metadata-Version: 2.1
Name: catway
Version: 1.1
Summary: Create tempmail based on https://mail.catway.org :D
Author-email: ZAID <y8838@hotmail.com>
Project-URL: Homepage, https://github.com/zaid5o5/catway
Project-URL: Issues, https://github.com/zaid5o5/catway/issues
Classifier: Programming Language :: Python :: 3
Classifier: License :: OSI Approved :: MIT License
Classifier: Operating System :: OS Independent
Requires-Python: >=3.8
License-File: LICENSE
Requires-Dist: aiohttp
Requires-Dist: asyncio
Requires-Dist: requests
